[
    {
        "scope": "source.php",
        "character": ";"
    },
    {
        "scope": "meta.class.php",
        "character": " {$0}"
    },
    {
        "scope": "meta.block.php",
        "character": ";"
    },
    {
        "scope": "meta.function.php",
        "character": ";"
    },
    {
        "scope": "entity.name.function.php",
        "character": " {$0}"
    },
    {
        "scope": "meta.function.parameters.php",
        "character": " {$0}"
    },
    {
        "scope": "meta.array.php",
        "character": ","
    },
    {
        "scope": "meta.array.php meta.function.php meta.block.php",
        "character": ";"
    },
    {
        "scope": "storage.type.class.php",
        "character": " {$0}"
    },
    {
        "scope": "meta.sequence.js",
        "character": ","
    },
    {
        "scope": "meta.object-literal.js",
        "character": ","
    },
    {
        "scope": "meta.structure.array.json",
        "character": ","
    },
    {
        "scope": "meta.structure.dictionary.json",
        "character": ","
    },
    {
        "scope": "punctuation.section.array.end.php",
        "character": ";"
    },
    {
        "scope": "meta.field.declaration.ts",
        "character": ";"
    },
    {
        "scope": "meta.object.member.ts",
        "character": ","
    },
    {
        "scope": "meta.objectliteral.ts",
        "character": "}"
    },
    {
        "scope": "meta.block.ts",
        "character": ";"
    },
    {
        "scope": "meta.class.ts",
        "character": "}"
    },
    {
        "scope": "meta.array.literal.ts",
        "character": ","
    }
]